Workbook

Sheet MRS
A1: ■ Purchase Requisition of Material / Manpower / Equipment Rental / ETC. | J1: DAESHIN PLANT
A2: PJT : SACE2 | D2: Division (In charge Name) : ADMIN MANAGER (Dong Chang Kim) | J2: Subcontract name (SAC2-SC-IK-SMP-01)
A3: MRS No : SAC2-DS-MRS-0348 | E3: =+L3 -> 46210 | L3: 46210
A4: No | B4: Item | D4: Specification (Model / Manufacturer / Size) | G4: Unit | H4: Qty | I4: Unit Price (SAR) (Exclude VAT) | J4: Total Price (SAR) (Exclude VAT) | K4: Vendor Name | L4: Remarks
A6: =ROW(A1) -> 1 | B6: Toilet Tissue | D6: Mouchoir | G6: BDL | H6: 20 | I6: 15.25 | J6: =H6*I6 -> 305 | K6: ATGC | L6: One time
A7: =ROW(A2) -> 2 | B7: Time Card Holder | D7: Super Deal | G7: EA | H7: 40 | I7: 75 | J7: =H7*I7 -> 3000
A8: =ROW(A3) -> 3 | B8: Paper Cup | D8: 9Oz Modern | G8: BOX | H8: 3 | I8: 64 | J8: =H8*I8 -> 192
A9: =ROW(A4) -> 4 | B9: Al Rai Juice Cocktail | D9: 27*250Ml | G9: EA | H9: 1500 | I9: 1.25 | J9: =H9*I9 -> 1875
A10: =ROW(A5) -> 5 | B10: Cake | G10: EA | H10: 1400 | I10: 1.25 | J10: =H10*I10 -> 1750
A11: =ROW(A6) -> 6 | B11: Sugar | D11: 1Kg*20 | G11: BOX | H11: 2 | I11: 70 | J11: =H11*I11 -> 140
A12: =ROW(A7) -> 7 | B12: Extension Cord Legrand | D12: 5Way 3Mtr | G12: EA | H12: 5 | I12: 80 | J12: =H12*I12 -> 400
A13: =ROW(A8) -> 8 | B13: Highlighter | D13: Deli,Yellow | G13: PKT | H13: 20 | I13: 11 | J13: =H13*I13 -> 220
A14: =ROW(A9) -> 9 | B14: Board Marker | D14: Deli | G14: PKT | H14: 2 | I14: 12 | J14: =H14*I14 -> 24
A15: =ROW(A10) -> 10 | B15: Record Book | D15: A7 | G15: EA | H15: 10 | I15: 3 | J15: =H15*I15 -> 30
A16: =ROW(A11) -> 11 | B16: Soft Drinks | D16: Cola,7Up,Merinda | G16: BOX | H16: 10 | I16: 57 | J16: =H16*I16 -> 570
A17: =ROW(A12) -> 12 | B17: Safety Helmet | D17: 3M,Green | G17: EA | H17: 5 | I17: 46 | J17: =H17*I17 -> 230
A18: =ROW(A13) -> 13 | B18: Safety Shoes | D18: Voultex,46 | G18: PAIR | H18: 2 | I18: 95 | J18: =H18*I18 -> 190
A19: =ROW(A14) -> 14 | B19: Helmet Sticker | D19: Smp | G19: EA | H19: 2000 | I19: 1 | J19: =H19*I19 -> 2000
A20: =ROW(A15) -> 15 | B20: A3 Paper | D20: Atlas | G20: BOX | H20: 35 | I20: 153 | J20: =H20*I20 -> 5355
A21: =ROW(A16) -> 16 | B21: A3 Lamination Pouch | D21: Super Deal | G21: PKT | H21: 15 | I21: 55 | J21: =H21*I21 -> 825
A22: =ROW(A17) -> 17 | B22: Drum Unit | D22: C7100 | G22: EA | H22: 1 | I22: 1050 | J22: =H22*I22 -> 1050
A23: =ROW(A18) -> 18 | B23: Wired Mouse | G23: EA | H23: 5 | I23: 21 | J23: =H23*I23 -> 105
A24: =ROW(A19) -> 19 | B24: Green Helmet | D24: 3M,Round Type | G24: EA | H24: 5 | I24: 80 | J24: =H24*I24 -> 400
A25: =ROW(A20) -> 20 | B25: Garbage Bag | D25: 100Gln | G25: BDL | H25: 65 | I25: 41.5 | J25: =H25*I25 -> 2697.5
A26: =ROW(A21) -> 21 | B26: Safety Shoes K7 | G26: PAIR | H26: 200 | I26: 63.5 | J26: =H26*I26 -> 12700
A27: =ROW(A22) -> 22 | B27: Red Vest With Pocket | D27: L-100/M-100 | G27: EA | H27: 150 | I27: 11 | J27: =H27*I27 -> 1650
A28: =ROW(A23) -> 23 | B28: Igloo | D28: 10Gln | G28: EA | H28: 41 | I28: 97 | J28: =H28*I28 -> 3977
A29: =ROW(A24) -> 24 | B29: Motor Fullset | D29: 0.5Hp | G29: EA | H29: 2 | I29: 240 | J29: =H29*I29 -> 480
A30: =ROW(A25) -> 25 | B30: Safety Googles Vaultex | D30: Clear-1000/Dark-1000 | G30: EA | H30: 1000 | I30: 3 | J30: =H30*I30 -> 3000
A31: =ROW(A26) -> 26 | B31: Ricoh Toner Mpc6003 | D31: Yellow-3/Cyan-1 | G31: EA | H31: 2 | I31: 506 | J31: =H31*I31 -> 1012
A32: =ROW(A27) -> 27 | B32: Ricoh Toner Mpc6003 | D32: Black | G32: EA | H32: 1 | I32: 342 | J32: =H32*I32 -> 342
A33: =ROW(A28) -> 28 | B33: Whitner 12/Pkt | G33: PKT | H33: 2 | I33: 15 | J33: =H33*I33 -> 30
A34: =ROW(A29) -> 29 | B34: Wiper | G34: EA | H34: 5 | I34: 14 | J34: =H34*I34 -> 70
A35: =ROW(A30) -> 30 | B35: Stapler Big | D35: 30Sheet Kangaro | G35: EA | H35: 1 | I35: 37 | J35: =H35*I35 -> 37
A36: =ROW(A31) -> 31 | B36: Pocket Diary | D36: A5 | G36: EA | H36: 5 | I36: 5.25 | J36: =H36*I36 -> 26.25
A37: =ROW(A32) -> 32 | B37: Pocket Diary | D37: A6 | G37: EA | H37: 5 | I37: 4.25 | J37: =H37*I37 -> 21.25
A38: =ROW(A33) -> 33 | B38: Hana Water | D38: 1.50Ltr*6 | G38: BOX | H38: 200 | I38: 6.5 | J38: =H38*I38 -> 1300
A39: =ROW(A34) -> 34 | B39: Folding Chair | G39: EA | H39: 6 | I39: 80 | J39: =H39*I39 -> 480
A40: =ROW(A35) -> 35 | B40: Safety Vest Pocket With Logo | D40: M-100/L-100/Xl-50/Xxl- 100/Xxxl-30 | G40: EA | H40: 230 | I40: 17 | J40: =H40*I40 -> 3910
A41: =ROW(A36) -> 36 | B41: Office Chair | D41: Without Neck | G41: EA | H41: 4 | I41: 156 | J41: =H41*I41 -> 624
A42: =ROW(A37) -> 37 | B42: A4 Paper | D42: Atlas | G42: BOX | H42: 77 | I42: 76 | J42: =H42*I42 -> 5852
A43: =ROW(A38) -> 38 | B43: Nescafe Classic | D43: 190Gm | G43: EA | H43: 12 | I43: 24 | J43: =H43*I43 -> 288
A44: =ROW(A39) -> 39 | B44: Rabea Tea | G44: PKT | H44: 12 | I44: 10.41 | J44: =H44*I44 -> 124.92
A45: =ROW(A40) -> 40 | B45: Water Filter | D45: 1*100Pcs | G45: EA | H45: 100 | I45: 11 | J45: =H45*I45 -> 1100
A46: =ROW(A41) -> 41 | B46: Safety Helmet Yellow | D46: Gariox | G46: EA | H46: 50 | I46: 12 | J46: =H46*I46 -> 600
A47: =ROW(A42) -> 42 | B47: A4 Label Sticker | G47: PKT | H47: 4 | I47: 35 | J47: =H47*I47 -> 140
A48: =ROW(A43) -> 43 | B48: White Board Marker | D48: Red-20/Blue-20,Deli | G48: PKT | H48: 10 | I48: 12 | J48: =H48*I48 -> 120
A49: =ROW(A44) -> 44 | B49: Xerox Drum Unit | G49: EA | H49: 2 | I49: 1050 | J49: =H49*I49 -> 2100
A50: =ROW(A45) -> 45 | B50: White Board | D50: 90*60,Super Deal | G50: EA | H50: 4 | I50: 44 | J50: =H50*I50 -> 176
A51: =ROW(A46) -> 46 | B51: Shampoo | D51: Head&Sholder 190Ml | G51: EA | H51: 2 | I51: 13 | J51: =H51*I51 -> 26
A52: =ROW(A47) -> 47 | B52: Tooth Paste | D52: Sensodyne | G52: EA | H52: 10 | I52: 30 | J52: =H52*I52 -> 300
A53: =ROW(A48) -> 48 | B53: Tooth Brush | D53: Sensodyne | G53: EA | H53: 10 | I53: 7 | J53: =H53*I53 -> 70
A54: =ROW(A49) -> 49 | B54: Paper Clip | D54: 33Mm | G54: PKT | H54: 50 | I54: 2 | J54: =H54*I54 -> 100
A55: =ROW(A50) -> 50 | B55: Paper Clip | D55: 28Mm | G55: PKT | H55: 50 | I55: 1.9 | J55: =H55*I55 -> 95
A56: =ROW(A51) -> 51 | B56: Sticker | G56: EA | H56: 1000 | I56: 1 | J56: =H56*I56 -> 1000
A57: =ROW(A52) -> 52 | B57: Water Dispenser | D57: Geepas | G57: EA | H57: 1 | I57: 380 | J57: =H57*I57 -> 380
A58: =ROW(A53) -> 53 | B58: Gooday Biscuit | G58: BOX | H58: 2 | I58: 22 | J58: =H58*I58 -> 44
A59: =ROW(A54) -> 54 | B59: Time Card | D59: 100Pcs/Pkt | G59: PKT | H59: 60 | I59: 9 | J59: =H59*I59 -> 540
A60: =ROW(A55) -> 55 | B60: 2 Hole Punch | G60: EA | H60: 2 | I60: 29 | J60: =H60*I60 -> 58
A61: =ROW(A56) -> 56 | B61: Flag Man Vest | G61: EA | H61: 10 | I61: 11 | J61: =H61*I61 -> 110
A62: =ROW(A57) -> 57 | B62: Side Shield For Glass | G62: EA | H62: 3 | I62: 5 | J62: =H62*I62 -> 15
A63: =ROW(A58) -> 58 | B63: Toshiba Toner Tfc 425 | D63: Black | G63: EA | H63: 2 | I63: 385 | J63: =H63*I63 -> 770
A64: =ROW(A59) -> 59 | B64: Toshiba Toner Tfc 425 | D64: Yellow-2/Magenta-2 | G64: EA | H64: 2 | I64: 500 | J64: =H64*I64 -> 1000
A65: =ROW(A60) -> 60 | B65: Chair Wheel | D65: 4Pcs/Set | G65: PKT | H65: 10 | I65: 14.5 | J65: =H65*I65 -> 145
A66: =ROW(A61) -> 61 | B66: Facial Tissue | G66: PKT | H66: 5 | I66: 19.5 | J66: =H66*I66 -> 97.5
A67: =ROW(A62) -> 62 | B67: Dac Cleaner | D67: 3Ltr | G67: EA | H67: 12 | I67: 26 | J67: =H67*I67 -> 312
A68: =ROW(A63) -> 63 | B68: Spray Paint | D68: Black 12*1 | G68: BOX | H68: 1 | I68: 65 | J68: =H68*I68 -> 65
A69: =ROW(A64) -> 64 | B69: Hp Toner 106A | D69: Black | G69: EA | H69: 3 | I69: 237 | J69: =H69*I69 -> 711
A70: =ROW(A65) -> 65 | B70: Broom Brush | D70: Black | G70: EA | H70: 25 | I70: 12 | J70: =H70*I70 -> 300
A71: =ROW(A66) -> 66 | B71: Dove Soap | G71: EA | H71: 6 | I71: 6 | J71: =H71*I71 -> 36
A72: =ROW(A67) -> 67 | B72: Shampoo | D72: Head&Sholder,400Ml | G72: EA | H72: 2 | I72: 18 | J72: =H72*I72 -> 36
A73: =ROW(A68) -> 68 | B73: Wet Tissue | G73: EA | H73: 24 | I73: 8 | J73: =H73*I73 -> 192
A74: =ROW(A69) -> 69 | B74: Chin Strap | D74: Blue & White | G74: EA | H74: 150 | I74: 1.5 | J74: =H74*I74 -> 225
A75: =ROW(A70) -> 70 | B75: Cone Cup | D75: 5000Pcs | G75: BOX | H75: 1 | I75: 181 | J75: =H75*I75 -> 181
A76: =ROW(A71) -> 71 | B76: Lifboy Soap | G76: EA | H76: 10 | I76: 7.3 | J76: =H76*I76 -> 73
A77: =ROW(A72) -> 72 | B77: Xeroxtoner | D77: C 7100/7120 /C7125/C7130 Black | G77: EA | H77: 3 | I77: 350 | J77: =H77*I77 -> 1050
A78: =ROW(A73) -> 73 | B78: Xeroxtoner | D78: C 7100/7120 /C7125/C7130 Yellow | G78: EA | H78: 2 | I78: 450 | J78: =H78*I78 -> 900
A79: =ROW(A74) -> 74 | B79: Xeroxtoner | D79: C 7100/7120 /C7125/C7130 Majenta | G79: EA | H79: 2 | I79: 450 | J79: =H79*I79 -> 900
A80: =ROW(A75) -> 75 | B80: Xeroxtoner | D80: C 7100/7120 /C7125/C7130 Cyan | G80: EA | H80: 1 | I80: 450 | J80: =H80*I80 -> 450
A81: =ROW(A76) -> 76 | B81: Xerox C7130 Drum Unit | G81: EA | H81: 1 | I81: 1080 | J81: =H81*I81 -> 1080
A82: =ROW(A77) -> 77 | B82: Time Crd Punching Machine | G82: EA | H82: 5 | I82: 610 | J82: =H82*I82 -> 3050
A83: =ROW(A78) -> 78 | B83: A4 Lamination Pouch | D83: Super Deal | G83: PKT | H83: 10 | I83: 28.8 | J83: =H83*I83 -> 288
A84: =ROW(A79) -> 79 | B84: Laptop Charger | G84: EA | H84: 1 | I84: 160 | J84: =H84*I84 -> 160
A85: =ROW(A80) -> 80 | B85: Thermal Paste | G85: EA | H85: 1 | I85: 36 | J85: =H85*I85 -> 36
A86: =ROW(A81) -> 81 | B86: Kitchen Tissue | D86: Dimah,.350Mtr*6 | G86: BDL | H86: 5 | I86: 73 | J86: =H86*I86 -> 365
A87: =ROW(A82) -> 82 | B87: Cooler Tap | D87: Small | G87: EA | H87: 50 | I87: 3.15 | J87: =H87*I87 -> 157.5
A88: =ROW(A83) -> 83 | B88: Cooler Tap | D88: Big | G88: EA | H88: 100 | I88: 3.6 | J88: =H88*I88 -> 360
A89: =ROW(A84) -> 84 | B89: A3 Box File | D89: 10Pcs/Ctn | G89: BOX | H89: 3 | I89: 144 | J89: =H89*I89 -> 432
A90: =ROW(A85) -> 85 | B90: Binder Clip | D90: 25Mm,1" | G90: BOX | H90: 5 | I90: 24 | J90: =H90*I90 -> 120
A91: =ROW(A86) -> 86 | B91: Binder Clip | D91: 32Mm 1-1/4" | G91: BOX | H91: 5 | I91: 30 | J91: =H91*I91 -> 150
A92: =ROW(A87) -> 87 | B92: Envelops | D92: Atlas,115*225,White,25/Pkt | G92: PKT | H92: 25 | I92: 3.5 | J92: =H92*I92 -> 87.5
A93: =ROW(A88) -> 88 | B93: Trio Ball Pen | D93: 50Pcs/Pkt,Blue-20/Red-6 | G93: PKT | H93: 10 | I93: 20 | J93: =H93*I93 -> 200
A94: Purpose | I94: Sum | J94: =SUM(J6:J93) -> 78186.42
A95: * There will be an additional administration expense and financial expense (Depend on contract) deduction of total provision cost price.
S96: HEC | T96: PCM | U96: ADM | V96: PM
T98: / | U98: / | V98: /
O99: Requesting | P99: JV Area PIC | Q99: PCM (Subcon)
O100: Company | S100: HDEC | T100: PCM | U100: ADM | V100: PM
O102: / | P102: / | Q102: / | T102: / | U102: / | V102: /
T118: PROJECT MANAGER
...

Sheet MRS LIST
A1: ■ Purchase Requisition of Equipment Rental | J1: =+MRS!J1 -> DAESHIN PLANT
A2: =+MRS!A2 -> PJT : SACE2 | D2: =+MRS!D2 -> Division (In charge Name) : ADMIN MANAGER (Dong Chang Kim) | J2: =+MRS!J2 -> Subcontract name (SAC2-SC-IK-SMP-01)
A3: =+MRS!A3 -> MRS No : SAC2-DS-MRS-0348 | K3: =+MRS!L3 -> 46210
A4: No | B4: Item | D4: Specification (Model / Manufacturer / Size) | G4: Unit | H4: Q'ty | I4: Unit Price | J4: Total Price | K4: Remarks
A6: =+MRS!A6 -> 1 | B6: =MRS!B6 -> Toilet Tissue | D6: =MRS!D6 -> Mouchoir | G6: =MRS!G6 -> BDL | H6: =MRS!H6 -> 20 | I6: =MRS!I6 -> 15.25 | J6: =MRS!J6 -> 305
A7: =+MRS!A7 -> 2 | B7: =MRS!B7 -> Time Card Holder | D7: =MRS!D7 -> Super Deal | G7: =MRS!G7 -> EA | H7: =MRS!H7 -> 40 | I7: =MRS!I7 -> 75 | J7: =MRS!J7 -> 3000
A8: =+MRS!A8 -> 3 | B8: =MRS!B8 -> Paper Cup | D8: =MRS!D8 -> 9Oz Modern | G8: =MRS!G8 -> BOX | H8: =MRS!H8 -> 3 | I8: =MRS!I8 -> 64 | J8: =MRS!J8 -> 192
A9: =+MRS!A9 -> 4 | B9: =MRS!B9 -> Al Rai Juice Cocktail | D9: =MRS!D9 -> 27*250Ml | G9: =MRS!G9 -> EA | H9: =MRS!H9 -> 1500 | I9: =MRS!I9 -> 1.25 | J9: =MRS!J9 -> 1875
A10: =+MRS!A10 -> 5 | B10: =MRS!B10 -> Cake | D10: =MRS!D10 | G10: =MRS!G10 -> EA | H10: =MRS!H10 -> 1400 | I10: =MRS!I10 -> 1.25 | J10: =MRS!J10 -> 1750
A11: =+MRS!A11 -> 6 | B11: =MRS!B11 -> Sugar | D11: =MRS!D11 -> 1Kg*20 | G11: =MRS!G11 -> BOX | H11: =MRS!H11 -> 2 | I11: =MRS!I11 -> 70 | J11: =MRS!J11 -> 140
A12: =+MRS!A12 -> 7 | B12: =MRS!B12 -> Extension Cord Legrand | D12: =MRS!D12 -> 5Way 3Mtr | G12: =MRS!G12 -> EA | H12: =MRS!H12 -> 5 | I12: =MRS!I12 -> 80 | J12: =MRS!J12 -> 400
A13: =+MRS!A13 -> 8 | B13: =MRS!B13 -> Highlighter | D13: =MRS!D13 -> Deli,Yellow | G13: =MRS!G13 -> PKT | H13: =MRS!H13 -> 20 | I13: =MRS!I13 -> 11 | J13: =MRS!J13 -> 220
A14: =+MRS!A14 -> 9 | B14: =MRS!B14 -> Board Marker | D14: =MRS!D14 -> Deli | G14: =MRS!G14 -> PKT | H14: =MRS!H14 -> 2 | I14: =MRS!I14 -> 12 | J14: =MRS!J14 -> 24
A15: =+MRS!A15 -> 10 | B15: =MRS!B15 -> Record Book | D15: =MRS!D15 -> A7 | G15: =MRS!G15 -> EA | H15: =MRS!H15 -> 10 | I15: =MRS!I15 -> 3 | J15: =MRS!J15 -> 30
A16: =+MRS!A16 -> 11 | B16: =MRS!B16 -> Soft Drinks | D16: =MRS!D16 -> Cola,7Up,Merinda | G16: =MRS!G16 -> BOX | H16: =MRS!H16 -> 10 | I16: =MRS!I16 -> 57 | J16: =MRS!J16 -> 570
A17: =+MRS!A17 -> 12 | B17: =MRS!B17 -> Safety Helmet | D17: =MRS!D17 -> 3M,Green | G17: =MRS!G17 -> EA | H17: =MRS!H17 -> 5 | I17: =MRS!I17 -> 46 | J17: =MRS!J17 -> 230
... A21: =+MRS!A21 -> 16 | B21: =MRS!B21 -> A3 Lamination Pouch | D21: =MRS!D21 -> Super Deal | G21: =MRS!G21 -> PKT | H21: =MRS!H21 -> 15 | I21: =MRS!I21 -> 55 | J21: =MRS!J21 -> 825
A22: =MRS!A22 -> 17 | C22: =MRS!C22 -> 0 | F22: =MRS!F22 -> 0 | G22: =MRS!G22 -> EA | H22: =MRS!H22 -> 1 | I22: =MRS!I22 -> 1050 | J22: =MRS!J22 -> 1050
A23: =MRS!A23 -> 18 | C23: =MRS!C23 -> 0 | F23: =MRS!F23 -> 0 | G23: =MRS!G23 -> EA | H23: =MRS!H23 -> 5 | I23: =MRS!I23 -> 21 | J23: =MRS!J23 -> 105
A24: =MRS!A24 -> 19 | C24: =MRS!C24 -> 0 | F24: =MRS!F24 -> 0 | G24: =MRS!G24 -> EA | H24: =MRS!H24 -> 5 | I24: =MRS!I24 -> 80 | J24: =MRS!J24 -> 400
A25: =MRS!A25 -> 20 | C25: =MRS!C25 -> 0 | F25: =MRS!F25 -> 0 | G25: =MRS!G25 -> BDL | H25: =MRS!H25 -> 65 | I25: =MRS!I25 -> 41.5 | J25: =MRS!J25 -> 2697.5
A26: =MRS!A26 -> 21 | C26: =MRS!C26 -> 0 | F26: =MRS!F26 -> 0 | G26: =MRS!G26 -> PAIR | H26: =MRS!H26 -> 200 | I26: =MRS!I26 -> 63.5 | J26: =MRS!J26 -> 12700
A27: =MRS!A27 -> 22 | C27: =MRS!C27 -> 0 | F27: =MRS!F27 -> 0 | G27: =MRS!G27 -> EA | H27: =MRS!H27 -> 150 | I27: =MRS!I27 -> 11 | J27: =MRS!J27 -> 1650
A28: =MRS!A28 -> 23 | C28: =MRS!C28 -> 0 | F28: =MRS!F28 -> 0 | G28: =MRS!G28 -> EA | H28: =MRS!H28 -> 41 | I28: =MRS!I28 -> 97 | J28: =MRS!J28 -> 3977
A29: =MRS!A29 -> 24 | C29: =MRS!C29 -> 0 | F29: =MRS!F29 -> 0 | G29: =MRS!G29 -> EA | H29: =MRS!H29 -> 2 | I29: =MRS!I29 -> 240 | J29: =MRS!J29 -> 480
A30: =MRS!A30 -> 25 | C30: =MRS!C30 -> 0 | F30: =MRS!F30 -> 0 | G30: =MRS!G30 -> EA | H30: =MRS!H30 -> 1000 | I30: =MRS!I30 -> 3 | J30: =MRS!J30 -> 3000

Sheet PO 1st page
M2: BRANCH OF HYUNDAI ENG. & CONST. CO., LTD.
M3: P. O. Box 77249, Al Khobar 31952
M4: kingdom of Saudi Arabia
B5: C.R. 2051041774 & VAT No.: 300000504500003 | M5: Tel: +966-13-845-1088
M6: Fax: +966-13-845-1099
B9: TO: | C9: ATGC(Alrmooz Technical for General Contracting Est.)
C10: CR No. : | D10: 2053026325 | J10: P/O Date: | K10: =MRS!L3 -> 46210
C11: VAT No. : | D11: 300900558400003 | J11: P/O No.: | K11: =SUBSTITUTE(SUBSTITUTE(+MRS!A3," MRS No : ",""),"-MRS","-PO") -> SAC2-DS-PO-0348
C12: In Charge : | D12: Muhammed Rafi | J12: (Please mention this No. in
D13: +966 57 5956527 / Email:info@alrmoozsa.com | J13: All future correspondence)
C14: P.O. Box 2746, Al-Jubail 31951 | J14: Quote Ref. : | K14: QUO-MAT-26070405
C15: Landline : +99 13 8022775. : Mobile : +966 583694645 | J15: Date- | K15: 46207
B18: PURCHASE ORDER
B20: WE ARE PLEASED TO PLACE AN ORDER WITH YOU FOR THE GOODS DESCRIBED BELOW. THE ORDER SHALL BE SUBJECT TO THE TERMS AND CONDITIONS SET OUR
B21: BELOW AND ATTACHED. PLEASE SIGN AND RETURN THE ENCLOSED COPY OF THIS ORDER AS CONFIRMATION OF YOUR ACCEPTANCE OF IT WITHIN A WEEK
B22: OTHERWISE THIS ORDER SHALL BE REGARDED AS BEING ACCEPTED BY YOU.
B25: 1 | C25: GOODS
C26: Office Materials | M26: [Please refer to attached Scope of supply & Quotation for more details]
B28: 2 | C28: P/O AMOUNT
C29: Material Value | E29: : | F29: ='PO 2nd page'!G94 -> 78186.42
C30: VAT 15% | E30: : | F30: ='PO 2nd page'!G95 -> 11727.963
C31: Total Amount | E31: : | F31: ='PO 2nd page'!G96 -> 89914.383
B33: 3 | C33: PAYMENT TERMS
C34: 100% Payment after Delivery within 35 days with submission of the following Documents.
C35: a) Tax E-Invoice (From Zakat, Tax and Customs Authority)
C36: b) Delivery/Dispatch Note [Counter signed by Site Representative]
B38: 4 | C38: DELIVERY TERMS
C39: Delivery by Seller to Jafurah HYUNDAI Laydown within a Week after receipt of PO.
B41: 5 | C41: OTHER TERMS AND CONDITIONS
C42: a) Any quantity rejected by the Buyer owing to its poor quality and non conformity of specification shall be replaced and re-delivered
C43: by Seller to Buyer at no extra costs
C44: b) Material Certificate, Data Sheet, Safety Data Sheet and other documents which may required by ARAMCO in material receiving
C45: inspection should be submitted to Buyer
C46: c) MTC / MSDS, Others, If required by Client
B48: 6 | C48: CONTACT POINT:
B49: - | C49: Delivery & Payment : Dong Chang Kim / Daeshin Admin. [ Mobile No. : +966 53 748 5762 / Email : kdchjs@daeshinplant.com ]
B50: - | C50: Commercial (Purchaser) : Youngkyu Choi / Daeshin Planning [ Mobile No. : +966 53 952 0931 / Email : ykchoi@daeshinplant.com ]
B51: - | C51: Invoicing : Nehal Kauser / HDEC Purchase PIC [ Mobile No. : +966 50 610 2363 / Email : nehal_kauser@hdec.co.kr ]
B53: 7 | C53: Bank Account Details:
B54: - | C54: ACCOUNT NAME | F54: ALRMOOZ TECHNICAL FOR GENERAL CONTRACTING EST. | P54: =UPPER(F54) -> ALRMOOZ TECHNICAL FOR GENERAL CONTRACTING EST.
B55: - | C55: ACCOUNT NUMBER | F55: 04161114000110
B56: - | C56: IBAN | F56: SA61 1000 0004 1611 1400 0110
B57: - | C57: BANK NAME | F57: THE NATIONAL COMMERCIAL BANK
B58: - | C58: SWIFT CODE | F58: NCBKSAJE
B59: - | C59: CURRENCY | F59: SAR
C60: Bank account changes are strictly prohibited. Payments will only be made to the account registered and approved in this Purchase Order.
B64: Client | J64: Contractor
B66: Signature: | J66: Signature:
B67: Name : DONG HWAN HAN | J67: Name : | K67: =D12 -> Muhammed Rafi
B68: Title : Administrative Manager | J68: Title : | K68: Senior Project Coordinator
B69: For and behalf of | J69: For and behalf of
B70: Branch of Hyundai Engineering and Const. Co., Ltd. (HDEC) | J70: =C9 -> ATGC(Alrmooz Technical for General Contracting Est.)
A71: Page 1/2

Sheet PO 2nd page
A2: PO NO. : | B2: =+'PO 1st page'!K11 -> SAC2-DS-PO-0348 | C2: Scope of Supply
A3: DATE : | B3: =+'PO 1st page'!K10 -> 46210 | E3: Jafurah Utilities, Sulfur and Interconnecting Systems(Pkg-2)
A4: S. NO | B4: DESCRIPTION | D4: QTY | E4: UNIT | F4: ='PO 1st page'!C9 -> ATGC(Alrmooz Technical for General Contracting Est.) | H4: Remarks (Details)
F5: Unit Price | G5: Total Amount
A6: =ROW(A1) -> 1 | B6: =MRS!B6&" "&MRS!D6 -> Toilet Tissue Mouchoir | D6: =MRS!G6 -> BDL | E6: =MRS!H6 -> 20 | F6: =MRS!I6 -> 15.25 | G6: =F6*E6 -> 305
A7: =ROW(A2) -> 2 | B7: =MRS!B7&" "&MRS!D7 -> Time Card Holder Super Deal | D7: =MRS!G7 -> EA | E7: =MRS!H7 -> 40 | F7: =MRS!I7 -> 75 | G7: =F7*E7 -> 3000
A8: =ROW(A3) -> 3 | B8: =MRS!B8&" "&MRS!D8 -> Paper Cup 9Oz Modern | D8: =MRS!G8 -> BOX | E8: =MRS!H8 -> 3 | F8: =MRS!I8 -> 64 | G8: =F8*E8 -> 192
A9: =ROW(A4) -> 4 | B9: =MRS!B9&" "&MRS!D9 -> Al Rai Juice Cocktail 27*250Ml | D9: =MRS!G9 -> EA | E9: =MRS!H9 -> 1500 | F9: =MRS!I9 -> 1.25 | G9: =F9*E9 -> 1875
A10: =ROW(A5) -> 5 | B10: =MRS!B10&" "&MRS!D10 -> Cake | D10: =MRS!G10 -> EA | E10: =MRS!H10 -> 1400 | F10: =MRS!I10 -> 1.25 | G10: =F10*E10 -> 1750
A11: =ROW(A6) -> 6 | B11: =MRS!B11&" "&MRS!D11 -> Sugar 1Kg*20 | D11: =MRS!G11 -> BOX | E11: =MRS!H11 -> 2 | F11: =MRS!I11 -> 70 | G11: =F11*E11 -> 140
A12: =ROW(A7) -> 7 | B12: =MRS!B12&" "&MRS!D12 -> Extension Cord Legrand 5Way 3Mtr | D12: =MRS!G12 -> EA | E12: =MRS!H12 -> 5 | F12: =MRS!I12 -> 80 | G12: =F12*E12 -> 400
A13: =ROW(A8) -> 8 | B13: =MRS!B13&" "&MRS!D13 -> Highlighter Deli,Yellow | D13: =MRS!G13 -> PKT | E13: =MRS!H13 -> 20 | F13: =MRS!I13 -> 11 | G13: =F13*E13 -> 220
A14: =ROW(A9) -> 9 | B14: =MRS!B14&" "&MRS!D14 -> Board Marker Deli | D14: =MRS!G14 -> PKT | E14: =MRS!H14 -> 2 | F14: =MRS!I14 -> 12 | G14: =F14*E14 -> 24
A15: =ROW(A10) -> 10 | B15: =MRS!B15&" "&MRS!D15 -> Record Book A7 | D15: =MRS!G15 -> EA | E15: =MRS!H15 -> 10 | F15: =MRS!I15 -> 3 | G15: =F15*E15 -> 30
A16: =ROW(A11) -> 11 | B16: =MRS!B16&" "&MRS!D16 -> Soft Drinks Cola,7Up,Merinda | D16: =MRS!G16 -> BOX | E16: =MRS!H16 -> 10 | F16: =MRS!I16 -> 57 | G16: =F16*E16 -> 570
A17: =ROW(A12) -> 12 | B17: =MRS!B17&" "&MRS!D17 -> Safety Helmet 3M,Green | D17: =MRS!G17 -> EA | E17: =MRS!H17 -> 5 | F17: =MRS!I17 -> 46 | G17: =F17*E17 -> 230
... A93: =ROW(A88) -> 88 | B93: =MRS!B93&" "&MRS!D93 -> Trio Ball Pen 50Pcs/Pkt,Blue-20/Red-6 | D93: =MRS!G93 -> PKT | E93: =MRS!H93 -> 10 | F93: =MRS!I93 -> 20 | G93: =F93*E93 -> 200
A94: Sub Total Amount | G94: =SUM(G6:G93) -> 78186.42
A95: VAT 15% | G95: =+G94*0.15 -> 11727.963
A96: Grand Total in SAR | G96: =G95+G94 -> 89914.383
A97: =" 1) Above Price are as per your quotation with ref "&'PO 1st page'!K14 -> 1) Above Price are as per your quotation with ref QUO-MAT-26070405
A98: 2) Details of each item are attached separately.
A100: Page 2/2
